PV_Circuit_Model/IV_jobs.cp311-win_amd64.pyd
PV_Circuit_Model/IV_jobs.cpp
PV_Circuit_Model/IV_jobs.pyx
PV_Circuit_Model/__init__.py
PV_Circuit_Model/circuit_model.py
PV_Circuit_Model/data_fitting.py
PV_Circuit_Model/data_fitting_tandem_cell.py
PV_Circuit_Model/device.py
PV_Circuit_Model/device_analysis.py
PV_Circuit_Model/ivkernel.cp311-win_amd64.pyd
PV_Circuit_Model/ivkernel.cpp
PV_Circuit_Model/ivkernel.h
PV_Circuit_Model/ivkernel_wrapper.cpp
PV_Circuit_Model/ivkernel_wrapper.pyx
PV_Circuit_Model/measurement.py
PV_Circuit_Model/utilities.py
PV_Circuit_Model/utilities_silicon.py
PV_Circuit_Model/parameters/constants.json
PV_Circuit_Model/parameters/get_scipy_constants.py
PV_Circuit_Model/parameters/silicon_constants.json
PV_Circuit_Model/parameters/solver_env_variables.json
PV_Circuit_Model/parameters/wafer_formats.json
examples/a01_make_solar_cell.py
examples/a02_make_PV_module.py
examples/a03_make_tandem_cell.py
examples/a04_fit_to_tandem_measurements.py
examples/a05_fit_to_topcon_cell_measurements.py
pv_circuit_model-0.6.0.dist-info/licenses/LICENSE
pv_circuit_model-0.6.0.dist-info/METADATA
pv_circuit_model-0.6.0.dist-info/WHEEL
pv_circuit_model-0.6.0.dist-info/top_level.txt
pv_circuit_model-0.6.0.dist-info/RECORD
