Metadata-Version: 2.4
Name: PV_Circuit_Model
Version: 0.6.0
Summary: PV Circuit model for cells, modules and components with additional tools for simulations and model fits to measurement data
Author: Johnson Wong
License: MIT
Project-URL: Homepage, https://github.com/griddler-j/PV_circuit_model
Project-URL: Documentation, https://griddler-j.github.io/PV_circuit_model/
Project-URL: Source, https://github.com/griddler-j/PV_circuit_model
Project-URL: Issues, https://github.com/griddler-j/PV_circuit_model/issues
Requires-Python: >=3.11
License-File: LICENSE
Requires-Dist: numpy>=2.0
Requires-Dist: matplotlib>=3.8.2
Requires-Dist: Shapely>=2.1.1
Requires-Dist: tqdm>=4.66.1
Requires-Dist: joblib>=1.3.2
Requires-Dist: bson>=0.5.10
Dynamic: license-file
